james_ericsson_hello_world_test/__init__.py
james_ericsson_hello_world_test-0.0.1.dist-info/licenses/LICENSE
james_ericsson_hello_world_test-0.0.1.dist-info/METADATA
james_ericsson_hello_world_test-0.0.1.dist-info/WHEEL
james_ericsson_hello_world_test-0.0.1.dist-info/top_level.txt
james_ericsson_hello_world_test-0.0.1.dist-info/RECORD
