Metadata-Version: 2.4
Name: James-Ericsson-Hello-World-Test
Version: 0.0.1
Summary: A minimal Hello World package
Author-email: James Ericsson <jamesericsson95@gmail.com>
License: MIT
Classifier: Programming Language :: Python :: 3
Classifier: License :: OSI Approved :: MIT License
Classifier: Operating System :: OS Independent
Requires-Python: >=3.9
License-File: LICENSE
Dynamic: license-file
